.DS_Store
pptx2md/__init__.py
pptx2md/__main__.py
pptx2md/global_var.py
pptx2md/outputter.py
pptx2md/parser.py
pptx2md/tools.py
wecode-pptx2md/__init__.py
wecode-pptx2md/__main__.py
wecode-pptx2md/global_var.py
wecode-pptx2md/outputter.py
wecode-pptx2md/parser.py
wecode-pptx2md/tools.py
wecode2md/__init__.py
wecode2md/__main__.py
wecode2md/global_var.py
wecode2md/outputter.py
wecode2md/parser.py
wecode2md/tools.py
wecode2md-0.0.1.dist-info/METADATA
wecode2md-0.0.1.dist-info/WHEEL
wecode2md-0.0.1.dist-info/entry_points.txt
wecode2md-0.0.1.dist-info/top_level.txt
wecode2md-0.0.1.dist-info/RECORD
