Metadata-Version: 2.1
Name: wecode2md
Version: 0.0.1
Summary: convert pptx to markdown with separator
Home-page: UNKNOWN
Author: Shubham Singh
Author-email: UNKNOWN
License: MIT Licence
Keywords: pip,pptx2md,wecode
Platform: UNKNOWN
Requires-Dist: python-pptx
Requires-Dist: rapidfuzz
Requires-Dist: pillow
